Metadata-Version: 1.0
Name: names-and-char-count
Version: 0.5
Summary: It makes random names and give you letter count
Home-page: UNKNOWN
Author: Lsolowiej
Author-email: lsolowiej@gmail.com
License: UNKNOWN
Platform: UNKNOWN
